{
  "nodes": [
    {
      "id": "jwtutil_generatetoken",
      "label": "Generate Token",
      "file_type": "code",
      "source_file": "src/main/java/com/civic/javacivic/security/JwtUtil.java",
      "source_location": null
    },
    {
      "id": "jwtutil_extractemail",
      "label": "Extract Email",
      "file_type": "code",
      "source_file": "src/main/java/com/civic/javacivic/security/JwtUtil.java",
      "source_location": null
    },
    {
      "id": "jwtutil_isvalid",
      "label": "Is Valid Token",
      "file_type": "code",
      "source_file": "src/main/java/com/civic/javacivic/security/JwtUtil.java",
      "source_location": null
    },
    {
      "id": "jwtutil_getclaims",
      "label": "Get Claims",
      "file_type": "code",
      "source_file": "src/main/java/com/civic/javacivic/security/JwtUtil.java",
      "source_location": null
    },
    {
      "id": "userdetailsserviceimpl_loaduserbyusername",
      "label": "Load User by Username",
      "file_type": "code",
      "source_file": "src/main/java/com/civic/javacivic/security/UserDetailsServiceImpl.java",
      "source_location": null
    },
    {
      "id": "jwtfilter_dofilterinternal",
      "label": "JWT Filter Do Filter Internal",
      "file_type": "code",
      "source_file": "src/main/java/com/civic/javacivic/security/JwtFilter.java",
      "source_location": null
    },
    {
      "id": "authjs_gettoken",
      "label": "Get Token from Storage",
      "file_type": "code",
      "source_file": "src/main/resources/static/js/auth.js",
      "source_location": null
    },
    {
      "id": "authjs_getrole",
      "label": "Get Role from Storage",
      "file_type": "code",
      "source_file": "src/main/resources/static/js/auth.js",
      "source_location": null
    },
    {
      "id": "authjs_getname",
      "label": "Get Name from Storage",
      "file_type": "code",
      "source_file": "src/main/resources/static/js/auth.js",
      "source_location": null
    },
    {
      "id": "authjs_logout",
      "label": "Logout Function",
      "file_type": "code",
      "source_file": "src/main/resources/static/js/auth.js",
      "source_location": null
    },
    {
      "id": "authjs_apifetch",
      "label": "Authenticated API Fetch",
      "file_type": "code",
      "source_file": "src/main/resources/static/js/auth.js",
      "source_location": null
    },
    {
      "id": "authjs_requireauth",
      "label": "Require Authentication Guard",
      "file_type": "code",
      "source_file": "src/main/resources/static/js/auth.js",
      "source_location": null
    },
    {
      "id": "login_html_handlelogin",
      "label": "Handle Login",
      "file_type": "code",
      "source_file": "src/main/resources/static/login.html",
      "source_location": null
    },
    {
      "id": "login_html_redirectbyrole",
      "label": "Redirect by Role",
      "file_type": "code",
      "source_file": "src/main/resources/static/login.html",
      "source_location": null
    },
    {
      "id": "register_html_handleregister",
      "label": "Handle Register",
      "file_type": "code",
      "source_file": "src/main/resources/static/register.html",
      "source_location": null
    },
    {
      "id": "index_html_redirectbyrole",
      "label": "Index Redirect by Role",
      "file_type": "code",
      "source_file": "src/main/resources/static/index.html",
      "source_location": null
    },
    {
      "id": "user_dashboard_html",
      "label": "User Dashboard Page",
      "file_type": "code",
      "source_file": "src/main/resources/static/user/dashboard.html",
      "source_location": null
    },
    {
      "id": "user_report_html",
      "label": "User Report Page",
      "file_type": "code",
      "source_file": "src/main/resources/static/user/report.html",
      "source_location": null
    },
    {
      "id": "user_mycomplaints_html",
      "label": "User My Complaints Page",
      "file_type": "code",
      "source_file": "src/main/resources/static/user/my-complaints.html",
      "source_location": null
    },
    {
      "id": "admin_dashboard_html",
      "label": "Admin Dashboard Page",
      "file_type": "code",
      "source_file": "src/main/resources/static/admin/dashboard.html",
      "source_location": null
    },
    {
      "id": "admin_complaints_html",
      "label": "Admin Complaints Page",
      "file_type": "code",
      "source_file": "src/main/resources/static/admin/complaints.html",
      "source_location": null
    },
    {
      "id": "admin_notifications_html",
      "label": "Admin Notifications Page",
      "file_type": "code",
      "source_file": "src/main/resources/static/admin/notifications.html",
      "source_location": null
    },
    {
      "id": "dept_dashboard_html",
      "label": "Dept Dashboard Page",
      "file_type": "code",
      "source_file": "src/main/resources/static/dept/dashboard.html",
      "source_location": null
    },
    {
      "id": "dept_complaints_html",
      "label": "Dept Complaints Page",
      "file_type": "code",
      "source_file": "src/main/resources/static/dept/complaints.html",
      "source_location": null
    },
    {
      "id": "dept_inprogress_html",
      "label": "Dept In Progress Page",
      "file_type": "code",
      "source_file": "src/main/resources/static/dept/in-progress.html",
      "source_location": null
    },
    {
      "id": "role_main_admin",
      "label": "Main Admin Role",
      "file_type": "code",
      "source_file": "src/main/resources/static/js/auth.js",
      "source_location": null
    },
    {
      "id": "role_dept_admin",
      "label": "Department Admin Role",
      "file_type": "code",
      "source_file": "src/main/resources/static/js/auth.js",
      "source_location": null
    },
    {
      "id": "role_user",
      "label": "User Role",
      "file_type": "code",
      "source_file": "src/main/resources/static/js/auth.js",
      "source_location": null
    },
    {
      "id": "jwtutil_secret_key",
      "label": "JWT Secret Key Configuration",
      "file_type": "code",
      "source_file": "src/main/java/com/civic/javacivic/security/JwtUtil.java",
      "source_location": null
    },
    {
      "id": "jwtutil_expiration",
      "label": "JWT Expiration Configuration",
      "file_type": "code",
      "source_file": "src/main/java/com/civic/javacivic/security/JwtUtil.java",
      "source_location": null
    }
  ],
  "edges": [
    {
      "source": "jwtfilter_dofilterinternal",
      "target": "jwtutil_isvalid",
      "relation": "calls",
      "confidence": "EXTRACTED",
      "confidence_score": 1.0,
      "source_file": "src/main/java/com/civic/javacivic/security/JwtFilter.java",
      "source_location": null,
      "weight": 1.0
    },
    {
      "source": "jwtfilter_dofilterinternal",
      "target": "jwtutil_extractemail",
      "relation": "calls",
      "confidence": "EXTRACTED",
      "confidence_score": 1.0,
      "source_file": "src/main/java/com/civic/javacivic/security/JwtFilter.java",
      "source_location": null,
      "weight": 1.0
    },
    {
      "source": "jwtfilter_dofilterinternal",
      "target": "userdetailsserviceimpl_loaduserbyusername",
      "relation": "calls",
      "confidence": "EXTRACTED",
      "confidence_score": 1.0,
      "source_file": "src/main/java/com/civic/javacivic/security/JwtFilter.java",
      "source_location": null,
      "weight": 1.0
    },
    {
      "source": "jwtutil_getclaims",
      "target": "jwtutil_isvalid",
      "relation": "calls",
      "confidence": "EXTRACTED",
      "confidence_score": 1.0,
      "source_file": "src/main/java/com/civic/javacivic/security/JwtUtil.java",
      "source_location": null,
      "weight": 1.0
    },
    {
      "source": "jwtutil_extractemail",
      "target": "jwtutil_getclaims",
      "relation": "calls",
      "confidence": "EXTRACTED",
      "confidence_score": 1.0,
      "source_file": "src/main/java/com/civic/javacivic/security/JwtUtil.java",
      "source_location": null,
      "weight": 1.0
    },
    {
      "source": "userdetailsserviceimpl_loaduserbyusername",
      "target": "jwtutil_extractemail",
      "relation": "semantically_similar_to",
      "confidence": "INFERRED",
      "confidence_score": 0.75,
      "source_file": "src/main/java/com/civic/javacivic/security/UserDetailsServiceImpl.java",
      "source_location": null,
      "weight": 1.0
    },
    {
      "source": "authjs_gettoken",
      "target": "login_html_handlelogin",
      "relation": "shares_data_with",
      "confidence": "INFERRED",
      "confidence_score": 0.8,
      "source_file": "src/main/resources/static/js/auth.js",
      "source_location": null,
      "weight": 1.0
    },
    {
      "source": "authjs_getrole",
      "target": "login_html_redirectbyrole",
      "relation": "calls",
      "confidence": "EXTRACTED",
      "confidence_score": 1.0,
      "source_file": "src/main/resources/static/js/auth.js",
      "source_location": null,
      "weight": 1.0
    },
    {
      "source": "authjs_getname",
      "target": "user_dashboard_html",
      "relation": "calls",
      "confidence": "EXTRACTED",
      "confidence_score": 1.0,
      "source_file": "src/main/resources/static/js/auth.js",
      "source_location": null,
      "weight": 1.0
    },
    {
      "source": "authjs_logout",
      "target": "login_html_handlelogin",
      "relation": "references",
      "confidence": "INFERRED",
      "confidence_score": 0.65,
      "source_file": "src/main/resources/static/js/auth.js",
      "source_location": null,
      "weight": 1.0
    },
    {
      "source": "authjs_requireauth",
      "target": "user_dashboard_html",
      "relation": "calls",
      "confidence": "EXTRACTED",
      "confidence_score": 1.0,
      "source_file": "src/main/resources/static/js/auth.js",
      "source_location": null,
      "weight": 1.0
    },
    {
      "source": "authjs_requireauth",
      "target": "user_report_html",
      "relation": "calls",
      "confidence": "EXTRACTED",
      "confidence_score": 1.0,
      "source_file": "src/main/resources/static/js/auth.js",
      "source_location": null,
      "weight": 1.0
    },
    {
      "source": "authjs_requireauth",
      "target": "user_mycomplaints_html",
      "relation": "calls",
      "confidence": "EXTRACTED",
      "confidence_score": 1.0,
      "source_file": "src/main/resources/static/js/auth.js",
      "source_location": null,
      "weight": 1.0
    },
    {
      "source": "authjs_requireauth",
      "target": "admin_dashboard_html",
      "relation": "calls",
      "confidence": "EXTRACTED",
      "confidence_score": 1.0,
      "source_file": "src/main/resources/static/js/auth.js",
      "source_location": null,
      "weight": 1.0
    },
    {
      "source": "authjs_requireauth",
      "target": "admin_complaints_html",
      "relation": "calls",
      "confidence": "EXTRACTED",
      "confidence_score": 1.0,
      "source_file": "src/main/resources/static/js/auth.js",
      "source_location": null,
      "weight": 1.0
    },
    {
      "source": "authjs_requireauth",
      "target": "admin_notifications_html",
      "relation": "calls",
      "confidence": "EXTRACTED",
      "confidence_score": 1.0,
      "source_file": "src/main/resources/static/js/auth.js",
      "source_location": null,
      "weight": 1.0
    },
    {
      "source": "authjs_requireauth",
      "target": "dept_dashboard_html",
      "relation": "calls",
      "confidence": "EXTRACTED",
      "confidence_score": 1.0,
      "source_file": "src/main/resources/static/js/auth.js",
      "source_location": null,
      "weight": 1.0
    },
    {
      "source": "authjs_requireauth",
      "target": "dept_complaints_html",
      "relation": "calls",
      "confidence": "EXTRACTED",
      "confidence_score": 1.0,
      "source_file": "src/main/resources/static/js/auth.js",
      "source_location": null,
      "weight": 1.0
    },
    {
      "source": "authjs_requireauth",
      "target": "dept_inprogress_html",
      "relation": "calls",
      "confidence": "EXTRACTED",
      "confidence_score": 1.0,
      "source_file": "src/main/resources/static/js/auth.js",
      "source_location": null,
      "weight": 1.0
    },
    {
      "source": "login_html_handlelogin",
      "target": "jwtutil_generatetoken",
      "relation": "conceptually_related_to",
      "confidence": "INFERRED",
      "confidence_score": 0.6,
      "source_file": "src/main/resources/static/login.html",
      "source_location": null,
      "weight": 1.0
    },
    {
      "source": "register_html_handleregister",
      "target": "jwtutil_generatetoken",
      "relation": "conceptually_related_to",
      "confidence": "INFERRED",
      "confidence_score": 0.6,
      "source_file": "src/main/resources/static/register.html",
      "source_location": null,
      "weight": 1.0
    },
    {
      "source": "index_html_redirectbyrole",
      "target": "authjs_getrole",
      "relation": "calls",
      "confidence": "EXTRACTED",
      "confidence_score": 1.0,
      "source_file": "src/main/resources/static/index.html",
      "source_location": null,
      "weight": 1.0
    },
    {
      "source": "login_html_redirectbyrole",
      "target": "authjs_getrole",
      "relation": "calls",
      "confidence": "EXTRACTED",
      "confidence_score": 1.0,
      "source_file": "src/main/resources/static/login.html",
      "source_location": null,
      "weight": 1.0
    },
    {
      "source": "login_html_handlelogin",
      "target": "authjs_getrole",
      "relation": "calls",
      "confidence": "EXTRACTED",
      "confidence_score": 1.0,
      "source_file": "src/main/resources/static/login.html",
      "source_location": null,
      "weight": 1.0
    },
    {
      "source": "login_html_handlelogin",
      "target": "authjs_getname",
      "relation": "calls",
      "confidence": "EXTRACTED",
      "confidence_score": 1.0,
      "source_file": "src/main/resources/static/login.html",
      "source_location": null,
      "weight": 1.0
    },
    {
      "source": "login_html_handlelogin",
      "target": "authjs_gettoken",
      "relation": "calls",
      "confidence": "EXTRACTED",
      "confidence_score": 1.0,
      "source_file": "src/main/resources/static/login.html",
      "source_location": null,
      "weight": 1.0
    },
    {
      "source": "register_html_handleregister",
      "target": "authjs_getrole",
      "relation": "calls",
      "confidence": "EXTRACTED",
      "confidence_score": 1.0,
      "source_file": "src/main/resources/static/register.html",
      "source_location": null,
      "weight": 1.0
    },
    {
      "source": "register_html_handleregister",
      "target": "authjs_getname",
      "relation": "calls",
      "confidence": "EXTRACTED",
      "confidence_score": 1.0,
      "source_file": "src/main/resources/static/register.html",
      "source_location": null,
      "weight": 1.0
    },
    {
      "source": "register_html_handleregister",
      "target": "authjs_gettoken",
      "relation": "calls",
      "confidence": "EXTRACTED",
      "confidence_score": 1.0,
      "source_file": "src/main/resources/static/register.html",
      "source_location": null,
      "weight": 1.0
    },
    {
      "source": "jwtutil_generatetoken",
      "target": "jwtutil_secret_key",
      "relation": "references",
      "confidence": "EXTRACTED",
      "confidence_score": 1.0,
      "source_file": "src/main/java/com/civic/javacivic/security/JwtUtil.java",
      "source_location": null,
      "weight": 1.0
    },
    {
      "source": "jwtutil_generatetoken",
      "target": "jwtutil_expiration",
      "relation": "references",
      "confidence": "EXTRACTED",
      "confidence_score": 1.0,
      "source_file": "src/main/java/com/civic/javacivic/security/JwtUtil.java",
      "source_location": null,
      "weight": 1.0
    },
    {
      "source": "jwtutil_getclaims",
      "target": "jwtutil_secret_key",
      "relation": "references",
      "confidence": "EXTRACTED",
      "confidence_score": 1.0,
      "source_file": "src/main/java/com/civic/javacivic/security/JwtUtil.java",
      "source_location": null,
      "weight": 1.0
    }
  ],
  "hyperedges": [
    {
      "id": "auth_flow_nodes",
      "label": "Authentication Flow Components",
      "nodes": [
        "jwtutil_generatetoken",
        "jwtutil_isvalid",
        "jwtfilter_dofilterinternal",
        "userdetailsserviceimpl_loaduserbyusername",
        "authjs_gettoken",
        "authjs_requireauth",
        "login_html_handlelogin",
        "register_html_handleregister"
      ],
      "relation": "participate_in",
      "confidence": "INFERRED",
      "confidence_score": 0.85,
      "source_file": "src/main/java/com/civic/javacivic/security/JwtUtil.java"
    },
    {
      "id": "role_based_access_nodes",
      "label": "Role-Based Access Control",
      "nodes": [
        "role_main_admin",
        "role_dept_admin",
        "role_user",
        "login_html_redirectbyrole",
        "index_html_redirectbyrole",
        "authjs_getrole"
      ],
      "relation": "implement",
      "confidence": "INFERRED",
      "confidence_score": 0.8,
      "source_file": "src/main/resources/static/js/auth.js"
    },
    {
      "id": "user_pages_auth_nodes",
      "label": "User Authenticated Pages",
      "nodes": [
        "user_dashboard_html",
        "user_report_html",
        "user_mycomplaints_html",
        "authjs_requireauth"
      ],
      "relation": "implement",
      "confidence": "INFERRED",
      "confidence_score": 0.78,
      "source_file": "src/main/resources/static/user/dashboard.html"
    }
  ],
  "input_tokens": 0,
  "output_tokens": 0
}
