{"nodes": [{"id": "authservice_login", "label": "Login", "file_type": "code", "source_file": "src/main/java/com/civic/javacivic/service/AuthService.java", "source_location": null}, {"id": "authservice_register", "label": "Register", "file_type": "code", "source_file": "src/main/java/com/civic/javacivic/service/AuthService.java", "source_location": null}, {"id": "authservice", "label": "AuthService", "file_type": "code", "source_file": "src/main/java/com/civic/javacivic/service/AuthService.java", "source_location": null}], "edges": [{"source": "authservice", "target": "userrepository", "relation": "depends_on", "confidence": "EXTRACTED", "confidence_score": 1.0, "source_file": "src/main/java/com/civic/javacivic/service/AuthService.java", "source_location": null, "weight": 1.0}, {"source": "authservice_register", "target": "registerrequest", "relation": "uses", "confidence": "INFERRED", "confidence_score": 0.9, "source_file": "src/main/java/com/civic/javacivic/service/AuthService.java", "source_location": null, "weight": 1.0}, {"source": "authservice_login", "target": "loginrequest", "relation": "uses", "confidence": "INFERRED", "confidence_score": 0.9, "source_file": "src/main/java/com/civic/javacivic/service/AuthService.java", "source_location": null, "weight": 1.0}, {"source": "authservice", "target": "securityconfig", "relation": "references", "confidence": "INFERRED", "confidence_score": 0.7, "source_file": "src/main/java/com/civic/javacivic/service/AuthService.java", "source_location": null, "weight": 1.0}], "hyperedges": []}